edgedb/abstract.py
edgedb/options.py
edgedb/describe.py
edgedb/enums.py
edgedb/color.py
edgedb/_version.py
edgedb/credentials.py
edgedb/transaction.py
edgedb/base_client.py
edgedb/__init__.py
edgedb/introspect.py
edgedb/blocking_client.py
edgedb/platform.py
edgedb/asyncio_client.py
edgedb/con_utils.py
edgedb/py.typed
edgedb/_taskgroup.py
edgedb/codegen.py
edgedb/datatypes/range.py
edgedb/datatypes/__init__.py
edgedb/datatypes/datatypes.py
edgedb/protocol/asyncio_proto.py
edgedb/protocol/protocol.py
edgedb/protocol/__init__.py
edgedb/protocol/blocking_proto.py
edgedb/ai/__init__.py
edgedb/ai/core.py
edgedb/ai/types.py
edgedb/scram/__init__.py
edgedb/scram/saslprep.py
edgedb/errors/tags.py
edgedb/errors/_base.py
edgedb/errors/__init__.py
edgedb/pgproto/__init__.py
edgedb/pgproto/types.py
edgedb/pgproto/pgproto.py
gel-3.1.0.dist-info/RECORD
gel-3.1.0.dist-info/WHEEL
gel-3.1.0.dist-info/entry_points.txt
gel-3.1.0.dist-info/top_level.txt
gel-3.1.0.dist-info/METADATA
gel-3.1.0.dist-info/licenses/LICENSE
gel/abstract.py
gel/options.py
gel/describe.py
gel/enums.py
gel/color.py
gel/_version.py
gel/credentials.py
gel/transaction.py
gel/base_client.py
gel/_testbase.py
gel/__init__.py
gel/introspect.py
gel/blocking_client.py
gel/platform.py
gel/cli.py
gel/asyncio_client.py
gel/con_utils.py
gel/py.typed
gel/connresource.py
gel/_taskgroup.py
gel/__main__.py
gel/datatypes/config_memory.pyx
gel/datatypes/relative_duration.pxd
gel/datatypes/__init__.pxd
gel/datatypes/date_duration.pyx
gel/datatypes/range.py
gel/datatypes/datatypes.pxd
gel/datatypes/__init__.py
gel/datatypes/enum.pyx
gel/datatypes/datatypes.pyx
gel/datatypes/date_duration.pxd
gel/datatypes/relative_duration.pyx
gel/datatypes/datatypes.cpython-312-darwin.so
gel/datatypes/config_memory.pxd
gel/protocol/asyncio_proto.cpython-312-darwin.so
gel/protocol/protocol.cpython-312-darwin.so
gel/protocol/protocol.pyx
gel/protocol/protocol_v0.pxd
gel/protocol/consts.pxi
gel/protocol/lru.pyx
gel/protocol/blocking_proto.pxd
gel/protocol/__init__.py
gel/protocol/asyncio_proto.pyx
gel/protocol/asyncio_proto.pxd
