Metadata-Version: 2.4
Name: gel
Version: 3.1.0
Summary: Official Gel Python Driver
Author: Gel Contributors
Author-email: "Gel Data Inc." <hello@geldata.com>
License: Apache License, Version 2.0
Project-URL: homepage, https://www.geldata.com
Project-URL: source, https://github.com/geldata/gel-python
Project-URL: documentation, https://docs.geldata.com/reference/clients/python
Project-URL: issues, https://github.com/geldata/gel-python/issues
Keywords: gel,edgedb,database,postgres
Classifier: Development Status :: 5 - Production/Stable
Classifier: Intended Audience :: Developers
Classifier: Intended Audience :: Information Technology
Classifier: Operating System :: POSIX
Classifier: Operating System :: MacOS :: MacOS X
Classifier: Operating System :: Microsoft :: Windows
Classifier: Programming Language :: Python :: 3 :: Only
Classifier: Programming Language :: Python :: 3.9
Classifier: Programming Language :: Python :: 3.10
Classifier: Programming Language :: Python :: 3.11
Classifier: Programming Language :: Python :: 3.12
Classifier: Programming Language :: Python :: 3.13
Classifier: Programming Language :: Python :: Implementation :: CPython
Classifier: Topic :: Database :: Front-Ends
Classifier: Topic :: Software Development :: Libraries :: Python Modules
Requires-Python: >=3.9.0
License-File: LICENSE
Requires-Dist: certifi>=2021.5.30; platform_system == "Windows"
Provides-Extra: test
Requires-Dist: pytest>=3.6.0; extra == "test"
Requires-Dist: pycodestyle~=2.11.1; extra == "test"
Requires-Dist: pyflakes~=3.2.0; extra == "test"
Requires-Dist: uvloop>=0.15.1; platform_system != "Windows" and extra == "test"
Provides-Extra: sqltest
Requires-Dist: SQLAlchemy>=2.0.0; extra == "sqltest"
Requires-Dist: sqlmodel>=0.0.22; extra == "sqltest"
Requires-Dist: Django~=5.1.3; extra == "sqltest"
Requires-Dist: psycopg2-binary>=2.9.10; extra == "sqltest"
Provides-Extra: doc
Requires-Dist: sphinx~=4.2.0; extra == "doc"
Requires-Dist: sphinxcontrib-asyncio~=0.3.0; extra == "doc"
Requires-Dist: sphinx_rtd_theme~=1.0.0; extra == "doc"
Provides-Extra: ai
Requires-Dist: httpx~=0.27.0; extra == "ai"
Requires-Dist: httpx-sse~=0.4.0; extra == "ai"
Dynamic: license-file
